Metadata-Version: 2.1
Name: djcall
Version: 0.4.2
Summary: Leverage uWSGI spooler and cron in Django
Home-page: https://yourlabs.io/oss/djcall
Author: James Pic
Author-email: jpic@yourlabs.org
License: UNKNOWN
Keywords: django uwsgi cache spooler
Platform: UNKNOWN
Classifier: Development Status :: 2 - Pre-Alpha
Classifier: Environment :: Web Environment
Classifier: Framework :: Django
Classifier: Intended Audience :: Developers
Classifier: License :: OSI Approved :: MIT License
Classifier: Operating System :: OS Independent
Classifier: Programming Language :: Python :: 3
Classifier: Topic :: Internet :: WWW/HTTP
Classifier: Topic :: Software Development :: Libraries :: Python Modules
Provides-Extra: django
Provides-Extra: example
